git_pythonpath
