Metadata-Version: 1.0
Name: git-pythonpath
Version: 0.1.1
Summary: Temporarily add code in a git repo to python path.
Home-page: https://github.com/dean-shaff/git-pythonpath
Author: Dean Shaff
Author-email: dean.shaff@gmail.com
License: UNKNOWN
Keywords: git
Platform: UNKNOWN
